beeai_cli/__init__.py
beeai_cli/api.py
beeai_cli/async_typer.py
beeai_cli/auth_manager.py
beeai_cli/configuration.py
beeai_cli/console.py
beeai_cli/utils.py
beeai_cli/commands/__init__.py
beeai_cli/commands/agent.py
beeai_cli/commands/build.py
beeai_cli/commands/mcp.py
beeai_cli/commands/model.py
beeai_cli/commands/self.py
beeai_cli/commands/server.py
beeai_cli/commands/platform/__init__.py
beeai_cli/commands/platform/base_driver.py
beeai_cli/commands/platform/istio.py
beeai_cli/commands/platform/lima_driver.py
beeai_cli/commands/platform/wsl_driver.py
beeai_cli/data/.gitignore
beeai_cli/data/helm-chart.tgz
beeai_cli-0.3.7.dist-info/METADATA
beeai_cli-0.3.7.dist-info/WHEEL
beeai_cli-0.3.7.dist-info/entry_points.txt
beeai_cli-0.3.7.dist-info/RECORD
