Metadata-Version: 2.3
Name: beeai-cli
Version: 0.3.7
Summary: BeeAI CLI
Author: IBM Corp.
Requires-Dist: beeai-sdk==0.3.7
Requires-Dist: a2a-sdk==0.3.7
Requires-Dist: annotated-types==0.7.0
Requires-Dist: anyio==4.10.0
Requires-Dist: asgiref==3.9.1
Requires-Dist: asyncclick==8.2.2.2
Requires-Dist: attrs==25.3.0
Requires-Dist: authlib==1.6.3
Requires-Dist: cachetools==5.5.2
Requires-Dist: certifi==2025.8.3
Requires-Dist: cffi==2.0.0 ; platform_python_implementation != 'PyPy'
Requires-Dist: charset-normalizer==3.4.3
Requires-Dist: click==8.2.1
Requires-Dist: colorama==0.4.6 ; sys_platform == 'win32'
Requires-Dist: cryptography==45.0.7
Requires-Dist: distro==1.9.0
Requires-Dist: faker==37.6.0
Requires-Dist: fastapi==0.116.1
Requires-Dist: gnureadline==8.2.13 ; sys_platform != 'win32'
Requires-Dist: google-api-core==2.25.1
Requires-Dist: google-auth==2.40.3
Requires-Dist: googleapis-common-protos==1.70.0
Requires-Dist: h11==0.16.0
Requires-Dist: httpcore==1.0.9
Requires-Dist: httpx==0.28.1
Requires-Dist: httpx-sse==0.4.1
Requires-Dist: idna==3.10
Requires-Dist: importlib-metadata==8.7.0
Requires-Dist: iniconfig==2.1.0
Requires-Dist: inquirerpy==0.3.4
Requires-Dist: janus==2.0.0
Requires-Dist: jiter==0.10.0
Requires-Dist: jsf==0.11.2
Requires-Dist: jsonschema==4.25.1
Requires-Dist: jsonschema-specifications==2025.9.1
Requires-Dist: markdown-it-py==4.0.0
Requires-Dist: mcp==1.13.1
Requires-Dist: mdurl==0.1.2
Requires-Dist: nodeenv==1.9.1
Requires-Dist: objprint==0.3.0
Requires-Dist: openai==1.107.1
Requires-Dist: opentelemetry-api==1.36.0
Requires-Dist: opentelemetry-exporter-otlp-proto-common==1.36.0
Requires-Dist: opentelemetry-exporter-otlp-proto-http==1.36.0
Requires-Dist: opentelemetry-instrumentation==0.57b0
Requires-Dist: opentelemetry-instrumentation-asgi==0.57b0
Requires-Dist: opentelemetry-instrumentation-fastapi==0.57b0
Requires-Dist: opentelemetry-proto==1.36.0
Requires-Dist: opentelemetry-sdk==1.36.0
Requires-Dist: opentelemetry-semantic-conventions==0.57b0
Requires-Dist: opentelemetry-util-http==0.57b0
Requires-Dist: packaging==25.0
Requires-Dist: pfzy==0.3.4
Requires-Dist: pluggy==1.6.0
Requires-Dist: prompt-toolkit==3.0.52
Requires-Dist: proto-plus==1.26.1
Requires-Dist: protobuf==6.32.0
Requires-Dist: psutil==7.0.0
Requires-Dist: pyasn1==0.6.1
Requires-Dist: pyasn1-modules==0.4.2
Requires-Dist: pycparser==2.23 ; implementation_name != 'PyPy' and platform_python_implementation != 'PyPy'
Requires-Dist: pydantic==2.11.7
Requires-Dist: pydantic-core==2.33.2
Requires-Dist: pydantic-settings==2.10.1
Requires-Dist: pygments==2.19.2
Requires-Dist: pyright==1.1.405
Requires-Dist: pytest==8.4.2
Requires-Dist: python-dotenv==1.1.1
Requires-Dist: python-multipart==0.0.20
Requires-Dist: pywin32==311 ; sys_platform == 'win32'
Requires-Dist: pyyaml==6.0.2
Requires-Dist: referencing==0.36.2
Requires-Dist: requests==2.32.5
Requires-Dist: rich==14.1.0
Requires-Dist: rpds-py==0.27.1
Requires-Dist: rsa==4.9.1
Requires-Dist: rstr==3.2.2
Requires-Dist: ruff==0.13.0
Requires-Dist: shellingham==1.5.4
Requires-Dist: smart-open==7.3.1
Requires-Dist: sniffio==1.3.1
Requires-Dist: sse-starlette==3.0.2
Requires-Dist: starlette==0.47.3
Requires-Dist: tenacity==9.1.2
Requires-Dist: tqdm==4.67.1
Requires-Dist: typer==0.17.4
Requires-Dist: typing-extensions==4.15.0
Requires-Dist: typing-inspection==0.4.1
Requires-Dist: tzdata==2025.2
Requires-Dist: urllib3==2.5.0
Requires-Dist: uvicorn==0.35.0
Requires-Dist: wcwidth==0.2.13
Requires-Dist: wheel==0.45.1
Requires-Dist: wrapt==1.17.3
Requires-Dist: zipp==3.23.0
Requires-Python: >=3.13, <3.14
